setup.py
vatsim_sso/__init__.py
vatsim_sso.egg-info/PKG-INFO
vatsim_sso.egg-info/SOURCES.txt
vatsim_sso.egg-info/dependency_links.txt
vatsim_sso.egg-info/requires.txt
vatsim_sso.egg-info/top_level.txt