Metadata-Version: 1.0
Name: vatsim-sso
Version: 1.0
Summary: Easy to use wrapper for vatsim sso
Home-page: https://bitbucket.org/nharasym/vatsim-sso
Author: Nick Harasym
Author-email: saitekx50@me.com
License: MIT Licence
Platform: UNKNOWN
